{
    "fcitx5-pinyin-moegirl": {
        "cargoLock": null,
        "date": null,
        "extract": null,
        "name": "fcitx5-pinyin-moegirl",
        "passthru": null,
        "pinned": false,
        "src": {
            "name": null,
            "sha256": "sha256-xGZ7sxELPlPo27oSCoDXQrligkmcw/fDexIFt/S0rqc=",
            "type": "url",
            "url": "https://github.com/outloudvi/mw2fcitx/releases/download/20260109/moegirl.dict"
        },
        "version": "20260109"
    },
    "fcitx5-pinyin-zhwiki": {
        "cargoLock": null,
        "date": null,
        "extract": null,
        "name": "fcitx5-pinyin-zhwiki",
        "passthru": null,
        "pinned": false,
        "src": {
            "name": null,
            "sha256": "sha256-1/KKfeRhor1LGYBrOHqLvxfK9Byv3AplzqVX3lRO50Y=",
            "type": "url",
            "url": "https://github.com/felixonmars/fcitx5-pinyin-zhwiki/releases/download/0.3.0/zhwiki-20251223.dict"
        },
        "version": "20251223"
    },
    "moviepilot-core": {
        "cargoLock": null,
        "date": null,
        "extract": null,
        "name": "moviepilot-core",
        "passthru": null,
        "pinned": false,
        "src": {
            "deepClone": false,
            "fetchSubmodules": false,
            "leaveDotGit": false,
            "name": null,
            "owner": "jxxghp",
            "repo": "MoviePilot",
            "rev": "v2.9.9",
            "sha256": "sha256-/gTMqACZjA9XVd6nFiy5aKV+GK+qhSbgYKlu2uIrqQQ=",
            "sparseCheckout": [],
            "type": "github"
        },
        "version": "v2.9.9"
    },
    "moviepilot-frontend": {
        "cargoLock": null,
        "date": null,
        "extract": null,
        "name": "moviepilot-frontend",
        "passthru": null,
        "pinned": false,
        "src": {
            "deepClone": false,
            "fetchSubmodules": false,
            "leaveDotGit": false,
            "name": null,
            "owner": "jxxghp",
            "repo": "MoviePilot-Frontend",
            "rev": "v2.9.9",
            "sha256": "sha256-Z2lyNdDXn2kZJGJ0aJQF8VSXE7rkOGxvsOrA+T6D+U4=",
            "sparseCheckout": [],
            "type": "github"
        },
        "version": "v2.9.9"
    },
    "moviepilot-plugins": {
        "cargoLock": null,
        "date": "2026-01-26",
        "extract": null,
        "name": "moviepilot-plugins",
        "passthru": null,
        "pinned": false,
        "src": {
            "deepClone": false,
            "fetchSubmodules": false,
            "leaveDotGit": false,
            "name": null,
            "owner": "jxxghp",
            "repo": "MoviePilot-Plugins",
            "rev": "4d1b90abc8dce3ac05a9912dcab7894eedb37d2f",
            "sha256": "sha256-OPt46DHRp2xU6GVLdCwHLTTzvnXgeO15SbOQwxN37O8=",
            "sparseCheckout": [],
            "type": "github"
        },
        "version": "4d1b90abc8dce3ac05a9912dcab7894eedb37d2f"
    },
    "moviepilot-resources": {
        "cargoLock": null,
        "date": "2026-01-22",
        "extract": null,
        "name": "moviepilot-resources",
        "passthru": null,
        "pinned": false,
        "src": {
            "deepClone": false,
            "fetchSubmodules": false,
            "leaveDotGit": false,
            "name": null,
            "owner": "jxxghp",
            "repo": "MoviePilot-Resources",
            "rev": "c03973c28080371fcf4db5702a3f3782e47d016e",
            "sha256": "sha256-2hHYQbOslvXzhqechM16iYF409NTmG7/1+47OVFv96I=",
            "sparseCheckout": [],
            "type": "github"
        },
        "version": "c03973c28080371fcf4db5702a3f3782e47d016e"
    },
    "sierra-breeze-enhanced-git": {
        "cargoLock": null,
        "date": "2025-10-14",
        "extract": null,
        "name": "sierra-breeze-enhanced-git",
        "passthru": null,
        "pinned": false,
        "src": {
            "deepClone": false,
            "fetchSubmodules": false,
            "leaveDotGit": false,
            "name": null,
            "owner": "kupiqu",
            "repo": "SierraBreezeEnhanced",
            "rev": "4a4f085aa5c48ad11071dee4e92289c2cc4a36cd",
            "sha256": "sha256-dOIC2EQqninEIktVK6dLctzN/IiQIRvp1Qmcop9h7Dw=",
            "sparseCheckout": [],
            "type": "github"
        },
        "version": "4a4f085aa5c48ad11071dee4e92289c2cc4a36cd"
    },
    "teamspeak-management-tools": {
        "cargoLock": null,
        "date": null,
        "extract": null,
        "name": "teamspeak-management-tools",
        "passthru": null,
        "pinned": false,
        "src": {
            "deepClone": false,
            "fetchSubmodules": false,
            "leaveDotGit": false,
            "name": null,
            "owner": "KunoiSayami",
            "repo": "teamspeak-management-tools.rs",
            "rev": "v6.0.2",
            "sha256": "sha256-NDoaCMJ4p7JWNtBBniS5A5TlopQWitIyT9V5DBzvFrI=",
            "sparseCheckout": [],
            "type": "github"
        },
        "version": "v6.0.2"
    }
}